peter_explains/__init__.py
peter_explains/api_key.py
peter_explains/cache.py
peter_explains/format.py
peter_explains/main.py
peter_explains/messages.py
peter_explains/peter_ai.py
peter_explains/prompts.py
peter_explains/py.typed
peter_explains/schema.py
peter_explains/utils.py
peter_explains-0.0.12.dist-info/METADATA
peter_explains-0.0.12.dist-info/WHEEL
peter_explains-0.0.12.dist-info/entry_points.txt
peter_explains-0.0.12.dist-info/RECORD
