Metadata-Version: 2.4
Name: peter-explains
Version: 0.0.12
Summary: Linux command explanations from Peter Griffin
Project-URL: Homepage, https://atick.dev/peter-explains/
Project-URL: Documentation, https://atick.dev/peter-explains/
Project-URL: Repository, https://github.com/atick-faisal/peter-explains
Project-URL: Bug Tracker, https://github.com/atick-faisal/peter-explains/issues
Project-URL: Changelog, https://github.com/atick-faisal/peter-explains/blob/master/CHANGELOG.md
Author-email: Atick Faisal <atickfaisal@gmail.com>
Maintainer-email: Atick Faisal <atickfaisal@gmail.com>
License-Expression: MIT
Keywords: command,family,griffin,guy,linux,peter
Classifier: Development Status :: 3 - Alpha
Classifier: Intended Audience :: Developers
Classifier: License :: OSI Approved :: MIT License
Classifier: Programming Language :: Python :: 3
Classifier: Programming Language :: Python :: 3.10
Classifier: Programming Language :: Python :: 3.11
Classifier: Programming Language :: Python :: 3.12
Classifier: Programming Language :: Python :: 3.13
Requires-Python: >=3.10
Requires-Dist: click>=8.1.8
Requires-Dist: colorama>=0.4.6
Requires-Dist: diskcache>=5.6.3
Requires-Dist: google-genai>=1.5.0
Requires-Dist: json-repair>=0.39.1
Requires-Dist: keyring>=25.6.0
Requires-Dist: ruff>=0.9.10
